slackbot_queue/__init__.py
slackbot_queue/slack_controller.py
slackbot_queue/utils.py
slackbot_queue-0.3.7.dist-info/LICENSE
slackbot_queue-0.3.7.dist-info/METADATA
slackbot_queue-0.3.7.dist-info/WHEEL
slackbot_queue-0.3.7.dist-info/top_level.txt
slackbot_queue-0.3.7.dist-info/RECORD
