Metadata-Version: 2.1
Name: slackbot-queue
Version: 0.3.7
Summary: Slackbot with a celery queue for long running tasks
Home-page: https://github.com/xtream1101/slackbot-queue
Author: Eddy Hintze
Author-email: eddy@hintze.co
License: MIT
Platform: UNKNOWN
Requires-Dist: celery (<5.0.0)
Requires-Dist: slackclient (==1.1.2)
